decoder/__init__.py
decoder/acp/__init__.py
decoder/acp/acp_agent.py
decoder/acp/entrypoint.py
decoder/acp/utils.py
decoder/acp/tools/__init__.py
decoder/acp/tools/base.py
decoder/acp/tools/session_update.py
decoder/acp/tools/builtins/bash.py
decoder/acp/tools/builtins/read_file.py
decoder/acp/tools/builtins/search_replace.py
decoder/acp/tools/builtins/todo.py
decoder/acp/tools/builtins/write_file.py
decoder/cli/__init__.py
decoder/cli/cli.py
decoder/cli/clipboard.py
decoder/cli/commands.py
decoder/cli/entrypoint.py
decoder/cli/history_manager.py
decoder/cli/terminal_setup.py
decoder/cli/autocompletion/__init__.py
decoder/cli/autocompletion/base.py
decoder/cli/autocompletion/path_completion.py
decoder/cli/autocompletion/slash_command.py
decoder/cli/textual_ui/__init__.py
decoder/cli/textual_ui/app.py
decoder/cli/textual_ui/app.tcss
decoder/cli/textual_ui/terminal_theme.py
decoder/cli/textual_ui/handlers/__init__.py
decoder/cli/textual_ui/handlers/event_handler.py
decoder/cli/textual_ui/screens/__init__.py
decoder/cli/textual_ui/screens/splash.py
decoder/cli/textual_ui/widgets/__init__.py
decoder/cli/textual_ui/widgets/approval_app.py
decoder/cli/textual_ui/widgets/compact.py
decoder/cli/textual_ui/widgets/config_app.py
decoder/cli/textual_ui/widgets/context_progress.py
decoder/cli/textual_ui/widgets/loading.py
decoder/cli/textual_ui/widgets/messages.py
decoder/cli/textual_ui/widgets/mode_indicator.py
decoder/cli/textual_ui/widgets/path_display.py
decoder/cli/textual_ui/widgets/spinner.py
decoder/cli/textual_ui/widgets/status_message.py
decoder/cli/textual_ui/widgets/tool_widgets.py
decoder/cli/textual_ui/widgets/tools.py
decoder/cli/textual_ui/widgets/utils.py
decoder/cli/textual_ui/widgets/welcome.py
decoder/cli/textual_ui/widgets/chat_input/__init__.py
decoder/cli/textual_ui/widgets/chat_input/body.py
decoder/cli/textual_ui/widgets/chat_input/completion_manager.py
decoder/cli/textual_ui/widgets/chat_input/completion_popup.py
decoder_cli-1.0.36.dist-info/METADATA
decoder_cli-1.0.36.dist-info/WHEEL
decoder_cli-1.0.36.dist-info/entry_points.txt
decoder_cli-1.0.36.dist-info/licenses/LICENSE
decoder_cli-1.0.36.dist-info/RECORD
